Workbook

Sheet Comece aqui
B2: Carnê-leão 2026 para quem recebe em dólar
B3: Planilha gratuita do Ganho Real. Lance seus pagamentos em dólar e veja o imposto estimado de cada mês, com as regras de 2026.
B5: Como usar
B6: 1. Na aba Pagamentos, lance cada pagamento: a data em que o dinheiro foi creditado a você, a plataforma e o valor bruto em dólares.
B7: 2. A cotação oficial e o valor em reais aparecem sozinhos (dólar de compra do Banco Central, aba Cotações).
B8: 3. Paga INSS, tem dependentes ou paga pensão alimentícia? Preencha a aba Deduções. Se não, pode pular.
B9: 4. Na aba Resumo do mês, veja quanto pagar de DARF e até quando.
B11: Legenda
B12: Célula amarela: você preenche.
B13: Célula branca: calculada pela planilha. Não precisa mexer.
B14: As abas estão protegidas, sem senha, para evitar apagar fórmulas sem querer (Revisão > Desproteger planilha).
B16: Regras usadas
... B34: Cotações do Banco Central consultadas em 26/10/2026.

Sheet Pagamentos
B2: Pagamentos recebidos em 2026
B3: Um pagamento por linha. Preencha só as colunas amarelas: data, plataforma e valor em dólares. | F3: Total em reais: | G3: =SUM(G7:G306) -> 0
B5: Data do recebimento | C5: Plataforma | D5: Valor bruto (US$) | E5: Mês | F5: Cotação usada (R$ por US$) | G5: Valor em reais (R$) | H5: Aviso
B6: 46027 | C6: Exemplo: Outlier | D6: 480 | E6: =IFERROR(IF(B6="","",IF(YEAR(B6)<>2026,"",MONTH(B6))),"") -> 1 | F6: =IF(E6="","",IF(INDEX('Cotações'!$E$6:$E$17,E6)="","",INDEX('Cotações'!$E$6:$E$17,E6))) -> 5.3923 | G6: =IF(OR(F6="",NOT(ISNUMBER(D6))),"",ROUND(D6*F6,2)) -> 2588.3 | H6: ← Exemplo: não entra no total
E7: =IFERROR(IF(B7="","",IF(YEAR(B7)<>2026,"",MONTH(B7))),"") | F7: =IF(E7="","",IF(INDEX('Cotações'!$E$6:$E$17,E7)="","",INDEX('Cotações'!$E$6:$E$17,E7))) | G7: =IF(OR(F7="",NOT(ISNUMBER(D7))),"",ROUND(D7*F7,2)) | H7: =IF(AND(B7="",D7=""),"",IF(B7="","Falta a data",IF(IFERROR(YEAR(B7),0)<>2026,"Use uma data de 2026",IF(D7="","Falta o valor",IF(NOT(ISNUMBER(D7)),"O valor precisa ser um número",IF(F7="","Falta a cotação deste mês (aba Cotações)",""))))))
E8: =IFERROR(IF(B8="","",IF(YEAR(B8)<>2026,"",MONTH(B8))),"") | F8: =IF(E8="","",IF(INDEX('Cotações'!$E$6:$E$17,E8)="","",INDEX('Cotações'!$E$6:$E$17,E8))) | G8: =IF(OR(F8="",NOT(ISNUMBER(D8))),"",ROUND(D8*F8,2)) | H8: =IF(AND(B8="",D8=""),"",IF(B8="","Falta a data",IF(IFERROR(YEAR(B8),0)<>2026,"Use uma data de 2026",IF(D8="","Falta o valor",IF(NOT(ISNUMBER(D8)),"O valor precisa ser um número",IF(F8="","Falta a cotação deste mês (aba Cotações)",""))))))
E9: =IFERROR(IF(B9="","",IF(YEAR(B9)<>2026,"",MONTH(B9))),"") | F9: =IF(E9="","",IF(INDEX('Cotações'!$E$6:$E$17,E9)="","",INDEX('Cotações'!$E$6:$E$17,E9))) | G9: =IF(OR(F9="",NOT(ISNUMBER(D9))),"",ROUND(D9*F9,2)) | H9: =IF(AND(B9="",D9=""),"",IF(B9="","Falta a data",IF(IFERROR(YEAR(B9),0)<>2026,"Use uma data de 2026",IF(D9="","Falta o valor",IF(NOT(ISNUMBER(D9)),"O valor precisa ser um número",IF(F9="","Falta a cotação deste mês (aba Cotações)",""))))))
E10: =IFERROR(IF(B10="","",IF(YEAR(B10)<>2026,"",MONTH(B10))),"") | F10: =IF(E10="","",IF(INDEX('Cotações'!$E$6:$E$17,E10)="","",INDEX('Cotações'!$E$6:$E$17,E10))) | G10: =IF(OR(F10="",NOT(ISNUMBER(D10))),"",ROUND(D10*F10,2)) | H10: =IF(AND(B10="",D10=""),"",IF(B10="","Falta a data",IF(IFERROR(YEAR(B10),0)<>2026,"Use uma data de 2026",IF(D10="","Falta o valor",IF(NOT(ISNUMBER(D10)),"O valor precisa ser um número",IF(F10="","Falta a cotação deste mês (aba Cotações)",""))))))
E11: =IFERROR(IF(B11="","",IF(YEAR(B11)<>2026,"",MONTH(B11))),"") | F11: =IF(E11="","",IF(INDEX('Cotações'!$E$6:$E$17,E11)="","",INDEX('Cotações'!$E$6:$E$17,E11))) | G11: =IF(OR(F11="",NOT(ISNUMBER(D11))),"",ROUND(D11*F11,2)) | H11: =IF(AND(B11="",D11=""),"",IF(B11="","Falta a data",IF(IFERROR(YEAR(B11),0)<>2026,"Use uma data de 2026",IF(D11="","Falta o valor",IF(NOT(ISNUMBER(D11)),"O valor precisa ser um número",IF(F11="","Falta a cotação deste mês (aba Cotações)",""))))))
E12: =IFERROR(IF(B12="","",IF(YEAR(B12)<>2026,"",MONTH(B12))),"") | F12: =IF(E12="","",IF(INDEX('Cotações'!$E$6:$E$17,E12)="","",INDEX('Cotações'!$E$6:$E$17,E12))) | G12: =IF(OR(F12="",NOT(ISNUMBER(D12))),"",ROUND(D12*F12,2)) | H12: =IF(AND(B12="",D12=""),"",IF(B12="","Falta a data",IF(IFERROR(YEAR(B12),0)<>2026,"Use uma data de 2026",IF(D12="","Falta o valor",IF(NOT(ISNUMBER(D12)),"O valor precisa ser um número",IF(F12="","Falta a cotação deste mês (aba Cotações)",""))))))
E13: =IFERROR(IF(B13="","",IF(YEAR(B13)<>2026,"",MONTH(B13))),"") | F13: =IF(E13="","",IF(INDEX('Cotações'!$E$6:$E$17,E13)="","",INDEX('Cotações'!$E$6:$E$17,E13))) | G13: =IF(OR(F13="",NOT(ISNUMBER(D13))),"",ROUND(D13*F13,2)) | H13: =IF(AND(B13="",D13=""),"",IF(B13="","Falta a data",IF(IFERROR(YEAR(B13),0)<>2026,"Use uma data de 2026",IF(D13="","Falta o valor",IF(NOT(ISNUMBER(D13)),"O valor precisa ser um número",IF(F13="","Falta a cotação deste mês (aba Cotações)",""))))))
E14: =IFERROR(IF(B14="","",IF(YEAR(B14)<>2026,"",MONTH(B14))),"") | F14: =IF(E14="","",IF(INDEX('Cotações'!$E$6:$E$17,E14)="","",INDEX('Cotações'!$E$6:$E$17,E14))) | G14: =IF(OR(F14="",NOT(ISNUMBER(D14))),"",ROUND(D14*F14,2)) | H14: =IF(AND(B14="",D14=""),"",IF(B14="","Falta a data",IF(IFERROR(YEAR(B14),0)<>2026,"Use uma data de 2026",IF(D14="","Falta o valor",IF(NOT(ISNUMBER(D14)),"O valor precisa ser um número",IF(F14="","Falta a cotação deste mês (aba Cotações)",""))))))
E15: =IFERROR(IF(B15="","",IF(YEAR(B15)<>2026,"",MONTH(B15))),"") | F15: =IF(E15="","",IF(INDEX('Cotações'!$E$6:$E$17,E15)="","",INDEX('Cotações'!$E$6:$E$17,E15))) | G15: =IF(OR(F15="",NOT(ISNUMBER(D15))),"",ROUND(D15*F15,2)) | H15: =IF(AND(B15="",D15=""),"",IF(B15="","Falta a data",IF(IFERROR(YEAR(B15),0)<>2026,"Use uma data de 2026",IF(D15="","Falta o valor",IF(NOT(ISNUMBER(D15)),"O valor precisa ser um número",IF(F15="","Falta a cotação deste mês (aba Cotações)",""))))))
E16: =IFERROR(IF(B16="","",IF(YEAR(B16)<>2026,"",MONTH(B16))),"") | F16: =IF(E16="","",IF(INDEX('Cotações'!$E$6:$E$17,E16)="","",INDEX('Cotações'!$E$6:$E$17,E16))) | G16: =IF(OR(F16="",NOT(ISNUMBER(D16))),"",ROUND(D16*F16,2)) | H16: =IF(AND(B16="",D16=""),"",IF(B16="","Falta a data",IF(IFERROR(YEAR(B16),0)<>2026,"Use uma data de 2026",IF(D16="","Falta o valor",IF(NOT(ISNUMBER(D16)),"O valor precisa ser um número",IF(F16="","Falta a cotação deste mês (aba Cotações)",""))))))
E17: =IFERROR(IF(B17="","",IF(YEAR(B17)<>2026,"",MONTH(B17))),"") | F17: =IF(E17="","",IF(INDEX('Cotações'!$E$6:$E$17,E17)="","",INDEX('Cotações'!$E$6:$E$17,E17))) | G17: =IF(OR(F17="",NOT(ISNUMBER(D17))),"",ROUND(D17*F17,2)) | H17: =IF(AND(B17="",D17=""),"",IF(B17="","Falta a data",IF(IFERROR(YEAR(B17),0)<>2026,"Use uma data de 2026",IF(D17="","Falta o valor",IF(NOT(ISNUMBER(D17)),"O valor precisa ser um número",IF(F17="","Falta a cotação deste mês (aba Cotações)",""))))))
E18: =IFERROR(IF(B18="","",IF(YEAR(B18)<>2026,"",MONTH(B18))),"") | F18: =IF(E18="","",IF(INDEX('Cotações'!$E$6:$E$17,E18)="","",INDEX('Cotações'!$E$6:$E$17,E18))) | G18: =IF(OR(F18="",NOT(ISNUMBER(D18))),"",ROUND(D18*F18,2)) | H18: =IF(AND(B18="",D18=""),"",IF(B18="","Falta a data",IF(IFERROR(YEAR(B18),0)<>2026,"Use uma data de 2026",IF(D18="","Falta o valor",IF(NOT(ISNUMBER(D18)),"O valor precisa ser um número",IF(F18="","Falta a cotação deste mês (aba Cotações)",""))))))
... E306: =IFERROR(IF(B306="","",IF(YEAR(B306)<>2026,"",MONTH(B306))),"") | F306: =IF(E306="","",IF(INDEX('Cotações'!$E$6:$E$17,E306)="","",INDEX('Cotações'!$E$6:$E$17,E306))) | G306: =IF(OR(F306="",NOT(ISNUMBER(D306))),"",ROUND(D306*F306,2)) | H306: =IF(AND(B306="",D306=""),"",IF(B306="","Falta a data",IF(IFERROR(YEAR(B306),0)<>2026,"Use uma data de 2026",IF(D306="","Falta o valor",IF(NOT(ISNUMBER(D306)),"O valor precisa ser um número",IF(F306="","Falta a cotação deste mês (aba Cotações)",""))))))

Sheet Resumo do mês
B2: Resumo do mês: quanto pagar de carnê-leão
B3: Tudo aqui é calculado a partir das abas Pagamentos e Deduções. Estimativa com as regras de 2026, não é orientação contábil.
B5: Nº | C5: Mês | D5: Recebido no mês (R$) | E5: Deduções usadas (R$) | F5: Base de cálculo (R$) | G5: Imposto pela tabela (R$) | H5: Redução 2026 (R$) | I5: Imposto do mês (R$) | J5: Saldo de meses anteriores (R$) | K5: DARF a pagar (R$) | L5: Vencimento | M5: Situação
B6: 1 | C6: Janeiro | D6: =SUMIFS('Pagamentos'!$G$7:$G$306,'Pagamentos'!$E$7:$E$306,$B6) -> 0 | E6: =IF(D6=0,0,'Deduções'!J6) -> 0 | F6: =MAX(0,D6-E6) -> 0 | G6: =MAX(0,ROUND(F6*INDEX('Tabelas'!$D$6:$D$10,MATCH(F6,'Tabelas'!$B$6:$B$10,1))-INDEX('Tabelas'!$E$6:$E$10,MATCH(F6,'Tabelas'!$B$6:$B$10,1)),2)) -> 0 | H6: =IF(D6<=0,0,IF(D6<='Tabelas'!$C$19,MIN(G6,'Tabelas'!$C$20),IF(D6<='Tabelas'!$C$21,MIN(G6,MAX(0,ROUND('Tabelas'!$C$22-'Tabelas'!$C$23*D6,2))),0))) -> 0 | I6: =ROUND(G6-H6,2) -> 0 | J6: 0 | K6: =IF(I6+J6>='Tabelas'!$C$27,ROUND(I6+J6,2),0) -> 0 | L6: =WORKDAY(EOMONTH(DATE(2026,B6,1),1)+1,-1,'Tabelas'!$B$32:$B$46) -> 46080 | M6: =IF(K6>0,"Pagar DARF (código 0190) até o vencimento",IF(I6+J6>0,"Menos de R$ 10: soma no mês seguinte",IF(D6=0,"Sem rendimentos lançados","Isento neste mês"))) -> Sem rendimentos lançados
B7: 2 | C7: Fevereiro | D7: =SUMIFS('Pagamentos'!$G$7:$G$306,'Pagamentos'!$E$7:$E$306,$B7) -> 0 | E7: =IF(D7=0,0,'Deduções'!J7) -> 0 | F7: =MAX(0,D7-E7) -> 0 | G7: =MAX(0,ROUND(F7*INDEX('Tabelas'!$D$6:$D$10,MATCH(F7,'Tabelas'!$B$6:$B$10,1))-INDEX('Tabelas'!$E$6:$E$10,MATCH(F7,'Tabelas'!$B$6:$B$10,1)),2)) -> 0 | H7: =IF(D7<=0,0,IF(D7<='Tabelas'!$C$19,MIN(G7,'Tabelas'!$C$20),IF(D7<='Tabelas'!$C$21,MIN(G7,MAX(0,ROUND('Tabelas'!$C$22-'Tabelas'!$C$23*D7,2))),0))) -> 0 | I7: =ROUND(G7-H7,2) -> 0 | J7: =IF(K6=0,ROUND(I6+J6,2),0) -> 0 | K7: =IF(I7+J7>='Tabelas'!$C$27,ROUND(I7+J7,2),0) -> 0 | L7: =WORKDAY(EOMONTH(DATE(2026,B7,1),1)+1,-1,'Tabelas'!$B$32:$B$46) -> 46112 | M7: =IF(K7>0,"Pagar DARF (código 0190) até o vencimento",IF(I7+J7>0,"Menos de R$ 10: soma no mês seguinte",IF(D7=0,"Sem rendimentos lançados","Isento neste mês"))) -> Sem rendimentos lançados
B8: 3 | C8: Março | D8: =SUMIFS('Pagamentos'!$G$7:$G$306,'Pagamentos'!$E$7:$E$306,$B8) -> 0 | E8: =IF(D8=0,0,'Deduções'!J8) -> 0 | F8: =MAX(0,D8-E8) -> 0 | G8: =MAX(0,ROUND(F8*INDEX('Tabelas'!$D$6:$D$10,MATCH(F8,'Tabelas'!$B$6:$B$10,1))-INDEX('Tabelas'!$E$6:$E$10,MATCH(F8,'Tabelas'!$B$6:$B$10,1)),2)) -> 0 | H8: =IF(D8<=0,0,IF(D8<='Tabelas'!$C$19,MIN(G8,'Tabelas'!$C$20),IF(D8<='Tabelas'!$C$21,MIN(G8,MAX(0,ROUND('Tabelas'!$C$22-'Tabelas'!$C$23*D8,2))),0))) -> 0 | I8: =ROUND(G8-H8,2) -> 0 | J8: =IF(K7=0,ROUND(I7+J7,2),0) -> 0 | K8: =IF(I8+J8>='Tabelas'!$C$27,ROUND(I8+J8,2),0) -> 0 | L8: =WORKDAY(EOMONTH(DATE(2026,B8,1),1)+1,-1,'Tabelas'!$B$32:$B$46) -> 46142 | M8: =IF(K8>0,"Pagar DARF (código 0190) até o vencimento",IF(I8+J8>0,"Menos de R$ 10: soma no mês seguinte",IF(D8=0,"Sem rendimentos lançados","Isento neste mês"))) -> Sem rendimentos lançados
B9: 4 | C9: Abril | D9: =SUMIFS('Pagamentos'!$G$7:$G$306,'Pagamentos'!$E$7:$E$306,$B9) -> 0 | E9: =IF(D9=0,0,'Deduções'!J9) -> 0 | F9: =MAX(0,D9-E9) -> 0 | G9: =MAX(0,ROUND(F9*INDEX('Tabelas'!$D$6:$D$10,MATCH(F9,'Tabelas'!$B$6:$B$10,1))-INDEX('Tabelas'!$E$6:$E$10,MATCH(F9,'Tabelas'!$B$6:$B$10,1)),2)) -> 0 | H9: =IF(D9<=0,0,IF(D9<='Tabelas'!$C$19,MIN(G9,'Tabelas'!$C$20),IF(D9<='Tabelas'!$C$21,MIN(G9,MAX(0,ROUND('Tabelas'!$C$22-'Tabelas'!$C$23*D9,2))),0))) -> 0 | I9: =ROUND(G9-H9,2) -> 0 | J9: =IF(K8=0,ROUND(I8+J8,2),0) -> 0 | K9: =IF(I9+J9>='Tabelas'!$C$27,ROUND(I9+J9,2),0) -> 0 | L9: =WORKDAY(EOMONTH(DATE(2026,B9,1),1)+1,-1,'Tabelas'!$B$32:$B$46) -> 46171 | M9: =IF(K9>0,"Pagar DARF (código 0190) até o vencimento",IF(I9+J9>0,"Menos de R$ 10: soma no mês seguinte",IF(D9=0,"Sem rendimentos lançados","Isento neste mês"))) -> Sem rendimentos lançados
B10: 5 | C10: Maio | D10: =SUMIFS('Pagamentos'!$G$7:$G$306,'Pagamentos'!$E$7:$E$306,$B10) -> 0 | E10: =IF(D10=0,0,'Deduções'!J10) -> 0 | F10: =MAX(0,D10-E10) -> 0 | G10: =MAX(0,ROUND(F10*INDEX('Tabelas'!$D$6:$D$10,MATCH(F10,'Tabelas'!$B$6:$B$10,1))-INDEX('Tabelas'!$E$6:$E$10,MATCH(F10,'Tabelas'!$B$6:$B$10,1)),2)) -> 0 | H10: =IF(D10<=0,0,IF(D10<='Tabelas'!$C$19,MIN(G10,'Tabelas'!$C$20),IF(D10<='Tabelas'!$C$21,MIN(G10,MAX(0,ROUND('Tabelas'!$C$22-'Tabelas'!$C$23*D10,2))),0))) -> 0 | I10: =ROUND(G10-H10,2) -> 0 | J10: =IF(K9=0,ROUND(I9+J9,2),0) -> 0 | K10: =IF(I10+J10>='Tabelas'!$C$27,ROUND(I10+J10,2),0) -> 0 | L10: =WORKDAY(EOMONTH(DATE(2026,B10,1),1)+1,-1,'Tabelas'!$B$32:$B$46) -> 46203 | M10: =IF(K10>0,"Pagar DARF (código 0190) até o vencimento",IF(I10+J10>0,"Menos de R$ 10: soma no mês seguinte",IF(D10=0,"Sem rendimentos lançados","Isento neste mês"))) -> Sem rendimentos lançados
B11: 6 | C11: Junho | D11: =SUMIFS('Pagamentos'!$G$7:$G$306,'Pagamentos'!$E$7:$E$306,$B11) -> 0 | E11: =IF(D11=0,0,'Deduções'!J11) -> 0 | F11: =MAX(0,D11-E11) -> 0 | G11: =MAX(0,ROUND(F11*INDEX('Tabelas'!$D$6:$D$10,MATCH(F11,'Tabelas'!$B$6:$B$10,1))-INDEX('Tabelas'!$E$6:$E$10,MATCH(F11,'Tabelas'!$B$6:$B$10,1)),2)) -> 0 | H11: =IF(D11<=0,0,IF(D11<='Tabelas'!$C$19,MIN(G11,'Tabelas'!$C$20),IF(D11<='Tabelas'!$C$21,MIN(G11,MAX(0,ROUND('Tabelas'!$C$22-'Tabelas'!$C$23*D11,2))),0))) -> 0 | I11: =ROUND(G11-H11,2) -> 0 | J11: =IF(K10=0,ROUND(I10+J10,2),0) -> 0 | K11: =IF(I11+J11>='Tabelas'!$C$27,ROUND(I11+J11,2),0) -> 0 | L11: =WORKDAY(EOMONTH(DATE(2026,B11,1),1)+1,-1,'Tabelas'!$B$32:$B$46) -> 46234 | M11: =IF(K11>0,"Pagar DARF (código 0190) até o vencimento",IF(I11+J11>0,"Menos de R$ 10: soma no mês seguinte",IF(D11=0,"Sem rendimentos lançados","Isento neste mês"))) -> Sem rendimentos lançados
B12: 7 | C12: Julho | D12: =SUMIFS('Pagamentos'!$G$7:$G$306,'Pagamentos'!$E$7:$E$306,$B12) -> 0 | E12: =IF(D12=0,0,'Deduções'!J12) -> 0 | F12: =MAX(0,D12-E12) -> 0 | G12: =MAX(0,ROUND(F12*INDEX('Tabelas'!$D$6:$D$10,MATCH(F12,'Tabelas'!$B$6:$B$10,1))-INDEX('Tabelas'!$E$6:$E$10,MATCH(F12,'Tabelas'!$B$6:$B$10,1)),2)) -> 0 | H12: =IF(D12<=0,0,IF(D12<='Tabelas'!$C$19,MIN(G12,'Tabelas'!$C$20),IF(D12<='Tabelas'!$C$21,MIN(G12,MAX(0,ROUND('Tabelas'!$C$22-'Tabelas'!$C$23*D12,2))),0))) -> 0 | I12: =ROUND(G12-H12,2) -> 0 | J12: =IF(K11=0,ROUND(I11+J11,2),0) -> 0 | K12: =IF(I12+J12>='Tabelas'!$C$27,ROUND(I12+J12,2),0) -> 0 | L12: =WORKDAY(EOMONTH(DATE(2026,B12,1),1)+1,-1,'Tabelas'!$B$32:$B$46) -> 46265 | M12: =IF(K12>0,"Pagar DARF (código 0190) até o vencimento",IF(I12+J12>0,"Menos de R$ 10: soma no mês seguinte",IF(D12=0,"Sem rendimentos lançados","Isento neste mês"))) -> Sem rendimentos lançados
B13: 8 | C13: Agosto | D13: =SUMIFS('Pagamentos'!$G$7:$G$306,'Pagamentos'!$E$7:$E$306,$B13) -> 0 | E13: =IF(D13=0,0,'Deduções'!J13) -> 0 | F13: =MAX(0,D13-E13) -> 0 | G13: =MAX(0,ROUND(F13*INDEX('Tabelas'!$D$6:$D$10,MATCH(F13,'Tabelas'!$B$6:$B$10,1))-INDEX('Tabelas'!$E$6:$E$10,MATCH(F13,'Tabelas'!$B$6:$B$10,1)),2)) -> 0 | H13: =IF(D13<=0,0,IF(D13<='Tabelas'!$C$19,MIN(G13,'Tabelas'!$C$20),IF(D13<='Tabelas'!$C$21,MIN(G13,MAX(0,ROUND('Tabelas'!$C$22-'Tabelas'!$C$23*D13,2))),0))) -> 0 | I13: =ROUND(G13-H13,2) -> 0 | J13: =IF(K12=0,ROUND(I12+J12,2),0) -> 0 | K13: =IF(I13+J13>='Tabelas'!$C$27,ROUND(I13+J13,2),0) -> 0 | L13: =WORKDAY(EOMONTH(DATE(2026,B13,1),1)+1,-1,'Tabelas'!$B$32:$B$46) -> 46295 | M13: =IF(K13>0,"Pagar DARF (código 0190) até o vencimento",IF(I13+J13>0,"Menos de R$ 10: soma no mês seguinte",IF(D13=0,"Sem rendimentos lançados","Isento neste mês"))) -> Sem rendimentos lançados
B14: 9 | C14: Setembro | D14: =SUMIFS('Pagamentos'!$G$7:$G$306,'Pagamentos'!$E$7:$E$306,$B14) -> 0 | E14: =IF(D14=0,0,'Deduções'!J14) -> 0 | F14: =MAX(0,D14-E14) -> 0 | G14: =MAX(0,ROUND(F14*INDEX('Tabelas'!$D$6:$D$10,MATCH(F14,'Tabelas'!$B$6:$B$10,1))-INDEX('Tabelas'!$E$6:$E$10,MATCH(F14,'Tabelas'!$B$6:$B$10,1)),2)) -> 0 | H14: =IF(D14<=0,0,IF(D14<='Tabelas'!$C$19,MIN(G14,'Tabelas'!$C$20),IF(D14<='Tabelas'!$C$21,MIN(G14,MAX(0,ROUND('Tabelas'!$C$22-'Tabelas'!$C$23*D14,2))),0))) -> 0 | I14: =ROUND(G14-H14,2) -> 0 | J14: =IF(K13=0,ROUND(I13+J13,2),0) -> 0 | K14: =IF(I14+J14>='Tabelas'!$C$27,ROUND(I14+J14,2),0) -> 0 | L14: =WORKDAY(EOMONTH(DATE(2026,B14,1),1)+1,-1,'Tabelas'!$B$32:$B$46) -> 46325 | M14: =IF(K14>0,"Pagar DARF (código 0190) até o vencimento",IF(I14+J14>0,"Menos de R$ 10: soma no mês seguinte",IF(D14=0,"Sem rendimentos lançados","Isento neste mês"))) -> Sem rendimentos lançados
B15: 10 | C15: Outubro | D15: =SUMIFS('Pagamentos'!$G$7:$G$306,'Pagamentos'!$E$7:$E$306,$B15) -> 0 | E15: =IF(D15=0,0,'Deduções'!J15) -> 0 | F15: =MAX(0,D15-E15) -> 0 | G15: =MAX(0,ROUND(F15*INDEX('Tabelas'!$D$6:$D$10,MATCH(F15,'Tabelas'!$B$6:$B$10,1))-INDEX('Tabelas'!$E$6:$E$10,MATCH(F15,'Tabelas'!$B$6:$B$10,1)),2)) -> 0 | H15: =IF(D15<=0,0,IF(D15<='Tabelas'!$C$19,MIN(G15,'Tabelas'!$C$20),IF(D15<='Tabelas'!$C$21,MIN(G15,MAX(0,ROUND('Tabelas'!$C$22-'Tabelas'!$C$23*D15,2))),0))) -> 0 | I15: =ROUND(G15-H15,2) -> 0 | J15: =IF(K14=0,ROUND(I14+J14,2),0) -> 0 | K15: =IF(I15+J15>='Tabelas'!$C$27,ROUND(I15+J15,2),0) -> 0 | L15: =WORKDAY(EOMONTH(DATE(2026,B15,1),1)+1,-1,'Tabelas'!$B$32:$B$46) -> 46356 | M15: =IF(K15>0,"Pagar DARF (código 0190) até o vencimento",IF(I15+J15>0,"Menos de R$ 10: soma no mês seguinte",IF(D15=0,"Sem rendimentos lançados","Isento neste mês"))) -> Sem rendimentos lançados
B16: 11 | C16: Novembro | D16: =SUMIFS('Pagamentos'!$G$7:$G$306,'Pagamentos'!$E$7:$E$306,$B16) -> 0 | E16: =IF(D16=0,0,'Deduções'!J16) -> 0 | F16: =MAX(0,D16-E16) -> 0 | G16: =MAX(0,ROUND(F16*INDEX('Tabelas'!$D$6:$D$10,MATCH(F16,'Tabelas'!$B$6:$B$10,1))-INDEX('Tabelas'!$E$6:$E$10,MATCH(F16,'Tabelas'!$B$6:$B$10,1)),2)) -> 0 | H16: =IF(D16<=0,0,IF(D16<='Tabelas'!$C$19,MIN(G16,'Tabelas'!$C$20),IF(D16<='Tabelas'!$C$21,MIN(G16,MAX(0,ROUND('Tabelas'!$C$22-'Tabelas'!$C$23*D16,2))),0))) -> 0 | I16: =ROUND(G16-H16,2) -> 0 | J16: =IF(K15=0,ROUND(I15+J15,2),0) -> 0 | K16: =IF(I16+J16>='Tabelas'!$C$27,ROUND(I16+J16,2),0) -> 0 | L16: =WORKDAY(EOMONTH(DATE(2026,B16,1),1)+1,-1,'Tabelas'!$B$32:$B$46) -> 46386 | M16: =IF(K16>0,"Pagar DARF (código 0190) até o vencimento",IF(I16+J16>0,"Menos de R$ 10: soma no mês seguinte",IF(D16=0,"Sem rendimentos lançados","Isento neste mês"))) -> Sem rendimentos lançados
B17: 12 | C17: Dezembro | D17: =SUMIFS('Pagamentos'!$G$7:$G$306,'Pagamentos'!$E$7:$E$306,$B17) -> 0 | E17: =IF(D17=0,0,'Deduções'!J17) -> 0 | F17: =MAX(0,D17-E17) -> 0 | G17: =MAX(0,ROUND(F17*INDEX('Tabelas'!$D$6:$D$10,MATCH(F17,'Tabelas'!$B$6:$B$10,1))-INDEX('Tabelas'!$E$6:$E$10,MATCH(F17,'Tabelas'!$B$6:$B$10,1)),2)) -> 0 | H17: =IF(D17<=0,0,IF(D17<='Tabelas'!$C$19,MIN(G17,'Tabelas'!$C$20),IF(D17<='Tabelas'!$C$21,MIN(G17,MAX(0,ROUND('Tabelas'!$C$22-'Tabelas'!$C$23*D17,2))),0))) -> 0 | I17: =ROUND(G17-H17,2) -> 0 | J17: =IF(K16=0,ROUND(I16+J16,2),0) -> 0 | K17: =IF(I17+J17>='Tabelas'!$C$27,ROUND(I17+J17,2),0) -> 0 | L17: =WORKDAY(EOMONTH(DATE(2026,B17,1),1)+1,-1,'Tabelas'!$B$32:$B$46) -> 46416 | M17: =IF(K17>0,"Pagar DARF (código 0190) até o vencimento",IF(I17+J17>0,"Menos de R$ 10: soma no mês seguinte",IF(D17=0,"Sem rendimentos lançados","Isento neste mês"))) -> Sem rendimentos lançados
C18: Total 2026 | D18: =SUM(D6:D17) -> 0 | I18: =SUM(I6:I17) -> 0 | K18: =SUM(K6:K17) -> 0
B20: Vencimento: último dia útil do mês seguinte ao recebimento. Pagar atrasado gera multa de 0,33% ao dia (até 20%) mais juros Selic.
B21: O DARF é gerado no Carnê-Leão Web (e-CAC, conta gov.br prata ou ouro). Lá, use a opção indicada na coluna "Opção mais vantajosa" da aba Deduções.
B22: Redução 2026: até R$ 5.000,00 no mês o imposto fica zero; de R$ 5.000,01 a R$ 7.350,00 a redução diminui aos poucos (detalhes na aba Tabelas).

Sheet Deduções
B2: Deduções (opcional)
B3: Preencha só se você paga INSS como autônomo, tem dependentes ou paga pensão alimentícia. Em branco, a planilha usa o desconto simplificado de R$ 607,20.
B5: Nº | C5: Mês | D5: INSS pago no mês (R$) | E5: Nº de dependentes | F5: Pensão alimentícia (R$) | G5: Outras deduções (R$) | H5: Deduções legais (R$) | I5: Desconto simplificado (R$) | J5: Usado no cálculo (R$) | K5: Opção mais vantajosa
B6: 1 | C6: Janeiro | H6: =D6+E6*'Tabelas'!$C$15+F6+G6 -> 0 | I6: ='Tabelas'!$C$14 -> 607.2 | J6: =MAX(H6,I6) -> 607.2 | K6: =IF(H6>I6,"Deduções legais","Desconto simplificado") -> Desconto simplificado
B7: 2 | C7: Fevereiro | H7: =D7+E7*'Tabelas'!$C$15+F7+G7 -> 0 | I7: ='Tabelas'!$C$14 -> 607.2 | J7: =MAX(H7,I7) -> 607.2 | K7: =IF(H7>I7,"Deduções legais","Desconto simplificado") -> Desconto simplificado
B8: 3 | C8: Março | H8: =D8+E8*'Tabelas'!$C$15+F8+G8 -> 0 | I8: ='Tabelas'!$C$14 -> 607.2 | J8: =MAX(H8,I8) -> 607.2 | K8: =IF(H8>I8,"Deduções legais","Desconto simplificado") -> Desconto simplificado
B9: 4 | C9: Abril | H9: =D9+E9*'Tabelas'!$C$15+F9+G9 -> 0 | I9: ='Tabelas'!$C$14 -> 607.2 | J9: =MAX(H9,I9) -> 607.2 | K9: =IF(H9>I9,"Deduções legais","Desconto simplificado") -> Desconto simplificado
B10: 5 | C10: Maio | H10: =D10+E10*'Tabelas'!$C$15+F10+G10 -> 0 | I10: ='Tabelas'!$C$14 -> 607.2 | J10: =MAX(H10,I10) -> 607.2 | K10: =IF(H10>I10,"Deduções legais","Desconto simplificado") -> Desconto simplificado
B11: 6 | C11: Junho | H11: =D11+E11*'Tabelas'!$C$15+F11+G11 -> 0 | I11: ='Tabelas'!$C$14 -> 607.2 | J11: =MAX(H11,I11) -> 607.2 | K11: =IF(H11>I11,"Deduções legais","Desconto simplificado") -> Desconto simplificado
B12: 7 | C12: Julho | H12: =D12+E12*'Tabelas'!$C$15+F12+G12 -> 0 | I12: ='Tabelas'!$C$14 -> 607.2 | J12: =MAX(H12,I12) -> 607.2 | K12: =IF(H12>I12,"Deduções legais","Desconto simplificado") -> Desconto simplificado
B13: 8 | C13: Agosto | H13: =D13+E13*'Tabelas'!$C$15+F13+G13 -> 0 | I13: ='Tabelas'!$C$14 -> 607.2 | J13: =MAX(H13,I13) -> 607.2 | K13: =IF(H13>I13,"Deduções legais","Desconto simplificado") -> Desconto simplificado
B14: 9 | C14: Setembro | H14: =D14+E14*'Tabelas'!$C$15+F14+G14 -> 0 | I14: ='Tabelas'!$C$14 -> 607.2 | J14: =MAX(H14,I14) -> 607.2 | K14: =IF(H14>I14,"Deduções legais","Desconto simplificado") -> Desconto simplificado
B15: 10 | C15: Outubro | H15: =D15+E15*'Tabelas'!$C$15+F15+G15 -> 0 | I15: ='Tabelas'!$C$14 -> 607.2 | J15: =MAX(H15,I15) -> 607.2 | K15: =IF(H15>I15,"Deduções legais","Desconto simplificado") -> Desconto simplificado
B16: 11 | C16: Novembro | H16: =D16+E16*'Tabelas'!$C$15+F16+G16 -> 0 | I16: ='Tabelas'!$C$14 -> 607.2 | J16: =MAX(H16,I16) -> 607.2 | K16: =IF(H16>I16,"Deduções legais","Desconto simplificado") -> Desconto simplificado
B17: 12 | C17: Dezembro | H17: =D17+E17*'Tabelas'!$C$15+F17+G17 -> 0 | I17: ='Tabelas'!$C$14 -> 607.2 | J17: =MAX(H17,I17) -> 607.2 | K17: =IF(H17>I17,"Deduções legais","Desconto simplificado") -> Desconto simplificado
B19: INSS: valor da guia do INSS paga neste mês, como contribuinte individual.
B20: Dependentes: R$ 189,59 por dependente, por mês. Pensão: só a paga por decisão judicial ou acordo homologado.
B21: Outras deduções: por exemplo, livro-caixa. Use só com orientação de um contador.

Sheet Cotações
B2: Cotações do dólar (PTAX de compra, Banco Central)
B3: Para cada mês de recebimento vale a cotação de compra do último dia útil da 1ª quinzena do mês anterior.
B5: Nº | C5: Mês do recebimento | D5: Data de referência | E5: Cotação de compra (R$ por US$) | F5: Fonte
B6: 1 | C6: Janeiro de 2026 | D6: 46006 | E6: 5.3923 | F6: Banco Central (PTAX), consultado em 26/10/2026
B7: 2 | C7: Fevereiro de 2026 | D7: 46037 | E7: 5.384 | F7: Banco Central (PTAX), consultado em 26/10/2026
B8: 3 | C8: Março de 2026 | D8: 46066 | E8: 5.2282 | F8: Banco Central (PTAX), consultado em 26/10/2026
B9: 4 | C9: Abril de 2026 | D9: 46094 | E9: 5.2535 | F9: Banco Central (PTAX), consultado em 26/10/2026
B10: 5 | C10: Maio de 2026 | D10: 46127 | E10: 4.9922 | F10: Banco Central (PTAX), consultado em 26/10/2026
B11: 6 | C11: Junho de 2026 | D11: 46157 | E11: 5.0648 | F11: Banco Central (PTAX), consultado em 26/10/2026
B12: 7 | C12: Julho de 2026 | D12: 46188 | E12: 5.0424 | F12: Banco Central (PTAX), consultado em 26/10/2026
B13: 8 | C13: Agosto de 2026 | D13: 46218 | E13: 5.0721 | F13: Banco Central (PTAX), consultado em 26/10/2026
B14: 9 | C14: Setembro de 2026 | D14: 46248 | E14: 5.223 | F14: Banco Central (PTAX), consultado em 26/10/2026
B15: 10 | C15: Outubro de 2026 | D15: 46280 | E15: 5.1484 | F15: Banco Central (PTAX), consultado em 26/10/2026
B16: 11 | C16: Novembro de 2026 | D16: 46310 | E16: 5.0515 | F16: Banco Central (PTAX), consultado em 26/10/2026
B17: 12 | C17: Dezembro de 2026 | D17: 46339 | F17: Preencha após 13/11/2026: cotação de compra desse dia no site do Banco Central
B19: Fonte: Banco Central do Brasil, PTAX, cotação de compra do dólar. Consulta: https://www.bcb.gov.br/estabilidadefinanceira/historicocotacoes
B20: Só a cotação de dezembro fica liberada para preencher. Para mudar outra, desproteja a planilha (Revisão > Desproteger planilha).

Sheet Tabelas
B2: Regras e tabelas usadas (2026)
B3: A planilha calcula tudo a partir destes valores. Se uma regra mudar, atualize aqui.
B4: Tabela progressiva mensal do IRPF (vigente desde maio de 2025)
B5: Base de cálculo acima de (R$) | C5: Até (R$) | D5: Alíquota | E5: Parcela a deduzir (R$)
B6: 0 | C6: 2428.8 | D6: 0 | E6: 0 | F6: Fonte: Lei nº 15.191/2025
B7: 2428.8 | C7: 2826.65 | D7: 0.075 | E7: 182.16
B8: 2826.65 | C8: 3751.05 | D8: 0.15 | E8: 394.16
B9: 3751.05 | C9: 4664.68 | D9: 0.225 | E9: 675.49
B10: 4664.68 | C10: sem limite | D10: 0.275 | E10: 908.73
B13: Deduções
B14: Desconto simplificado mensal (R$) | C14: 607.2 | D14: 25% da faixa isenta da tabela mensal; substitui as deduções legais
B15: Dedução por dependente, por mês (R$) | C15: 189.59 | D15: Fonte: Lei nº 9.250/1995
B18: Redução do imposto em 2026 (Lei nº 15.270/2025)
B19: Imposto zero para rendimento mensal até (R$) | C19: 5000
B20: Redução máxima nessa faixa (R$) | C20: 312.89
B21: Redução parcial para rendimento até (R$) | C21: 7350 | D21: De R$ 5.000,01 a R$ 7.350,00: redução = 978,62 − 0,133145 × rendimento do mês, nunca maior que o imposto.
B22: Redução parcial: valor fixo (R$) | C22: 978.62
B23: Redução parcial: fator sobre o rendimento | C23: 0.133145
B26: DARF
B27: Valor mínimo do DARF (R$) | C27: 10 | D27: Abaixo disso, o imposto é somado ao do mês seguinte
B28: Código do DARF (carnê-leão) | C28: 0190
B30: Dias sem expediente bancário (usados para calcular o vencimento)
B31: Data | C31: Feriado
B32: 46023 | C32: Confraternização Universal
B33: 46069 | C33: Carnaval
B34: 46070 | C34: Carnaval
B35: 46115 | C35: Sexta-feira Santa
B36: 46133 | C36: Tiradentes
B37: 46143 | C37: Dia do Trabalho
B38: 46177 | C38: Corpus Christi
B39: 46272 | C39: Independência
B40: 46307 | C40: Nossa Senhora Aparecida
B41: 46328 | C41: Finados
B42: 46341 | C42: Proclamação da República
B43: 46346 | C43: Consciência Negra
... B46: 46388 | C46: Confraternização Universal
